gplumey_de_toolkit/__init__.py
gplumey_de_toolkit/main.py
gplumey_de_toolkit-0.1.0.dist-info/METADATA
gplumey_de_toolkit-0.1.0.dist-info/WHEEL
gplumey_de_toolkit-0.1.0.dist-info/entry_points.txt
gplumey_de_toolkit-0.1.0.dist-info/RECORD
