Metadata-Version: 2.1
Name: gplumey-de-toolkit
Version: 0.1.0
Summary: 
Author: gplumey
Author-email: guillaume.plumey@gmail.com
Requires-Python: >=3.10,<4.0
Classifier: Programming Language :: Python :: 3
Classifier: Programming Language :: Python :: 3.10
Classifier: Programming Language :: Python :: 3.11
Classifier: Programming Language :: Python :: 3.12
Requires-Dist: click (>=8.1.7,<9.0.0)
